{
  "uuid": "746e460a-8711-4a32-a415-35ac73685143",
  "name": "Notification MessageDialog",
  "description": "Open a simple information, warning or error dialog",
  "extraSearchTerms": [
    "popup"
  ],
  "tags": [
    "eclipse",
    "jface",
    "swt"
  ],
  "code": "MessageDialog.${kind:link(openInformation, openWarning, openError)}(${shell:var(org.eclipse.swt.widgets.Shell)}, ${title:var(java.lang.String)}, ${question:var(java.lang.String)});\n${:import(org.eclipse.jface.dialogs.MessageDialog)}",
  "location": "JAVA_STATEMENTS",
  "dependencies": [
    {
      "groupId": "org.eclipse.swt",
      "artifactId": "org.eclipse.swt",
      "version": "0.0.0"
    },
    {
      "groupId": "jre",
      "artifactId": "jre",
      "version": "0.0.0"
    }
  ]
}